sphinx_tsegsearch/.DS_Store
sphinx_tsegsearch/__init__.py
sphinx_tsegsearch/static/splitQuery.js
sphinx_tsegsearch/static/tiny_segmenter.js
sphinx_tsegsearch/templates/search.html
sphinx_tsegsearch-1.2.dist-info/WHEEL
sphinx_tsegsearch-1.2.dist-info/METADATA
sphinx_tsegsearch-1.2.dist-info/RECORD
