Metadata-Version: 2.1
Name: sphinx-tsegsearch
Version: 1.2
Summary: Sphinx extension to split searchword with TinySegmenter
Home-page: https://github.com/whosaysni/sphinx-tsegsearch/
License: MIT
Keywords: sphinx,japanese,word,segmentation,search
Author: Yasushi Masuda
Author-email: whosaysni@gmail.com
Classifier: Development Status :: 3 - Alpha
Classifier: Environment :: Plugins
Classifier: Framework :: Sphinx :: Extension
Classifier: Intended Audience :: Developers
Classifier: License :: OSI Approved :: MIT License
Classifier: Operating System :: OS Independent
Classifier: Programming Language :: Python
Classifier: Programming Language :: Python :: 2
Classifier: Programming Language :: Python :: 2.7
Classifier: Programming Language :: Python :: 3
Classifier: Programming Language :: Python :: 3.10
Classifier: Programming Language :: Python :: 3.4
Classifier: Programming Language :: Python :: 3.5
Classifier: Programming Language :: Python :: 3.6
Classifier: Programming Language :: Python :: 3.7
Classifier: Programming Language :: Python :: 3.8
Classifier: Programming Language :: Python :: 3.9
Classifier: Topic :: Documentation :: Sphinx
Requires-Dist: install_requires
Requires-Dist: install_requires
Project-URL: Repository, https://github.com/whosaysni/sphinx-tsegsearch/
